README
setup.cfg
setup.py
cointop/__init__.py
cointop.egg-info/PKG-INFO
cointop.egg-info/SOURCES.txt
cointop.egg-info/dependency_links.txt
cointop.egg-info/top_level.txt