Metadata-Version: 1.1
Name: cointop
Version: 0.0.1
Summary: Cointop python package
Home-page: https://github.com/miguelmota/py-cointop
Author: Miguel Mota
Author-email: hello@miguelmota.com
License: MIT License
Download-URL: https://github.com/miguelmota/py-cointop/archive/master.zip
Keywords: cointop
Platform: UNKNOWN
